spotify_browser_token/__init__.py
SpotifyBrowserToken-0.0.1.dist-info/LICENSE.txt
SpotifyBrowserToken-0.0.1.dist-info/METADATA
SpotifyBrowserToken-0.0.1.dist-info/WHEEL
SpotifyBrowserToken-0.0.1.dist-info/top_level.txt
SpotifyBrowserToken-0.0.1.dist-info/RECORD
