Metadata-Version: 2.1
Name: SpotifyBrowserToken
Version: 0.0.1
Summary: Spotify Browser Token Generator
Home-page: https://github.com/raspi-chromecast-box/SpotifyBrowserToken
Author: raspichromecastbox
Author-email: raspiccbox03@gmail.com
License: UNKNOWN
Platform: UNKNOWN
Classifier: Programming Language :: Python :: 3
Classifier: License :: OSI Approved :: MIT License
Classifier: Operating System :: OS Independent
Requires-Python: >=3.6
